Workbook

Sheet Estimate
A1: =B3 -> Estimate name
A3: Client | B3: Swimming NSW | C3: Use Type = Header for section headings. | F3: GST % | G3: ='Rates & Settings'!B3 -> 0.1 | I3: Live quote summary
A4: Project | B4: Swimming NSW Website Redevelopment | C4: Header rows show subtotal in price column. | F4: Contingency % | G4: 0.1 | I4: Labour & materials | K4: =SUMIFS($K$12:$K$78,$A$12:$A$78,"Item") -> 630
A5: Prepared by | B5: Mettro | C5: Use Type = Item for inclusions. | F5: Discount % | G5: ='Rates & Settings'!B5 -> 0 | I5: Contingency | K5: =K4*$G$4 -> 0
C6: DO NOT delete price and line total fields | I6: Discount | K6: =-(K4+K5)*$G$5 -> 0
I7: Subtotal | K7: =(K4+K5)-K6 -> 630
I8: Total inc GST | K8: =K7*(1+$G$3) -> 693
A10: Type | B10: Scope / inclusion | C10: Price | D10: Role 1 | E10: Hrs | F10: Role 2 | G10: Hrs | H10: Role 3 | I10: Hrs | J10: Material cost | K10: Line total | L10: Section key
A12: Header | B12: Blueprint Strategy | C12: =IF($A12="Header",SUMIFS($K$12:$K$78,$L$12:$L$78,$L12),"") -> 630 | K12: =IF($A12="Item",IFERROR(VLOOKUP($D12,'Rates & Settings'!$A$9:$B$21,2,FALSE)*$E12,0)+IFERROR(VLOOKUP($F12,'Rates & Settings'!$A$9:$B$21,2,FALSE)*$G12,0)+IFERROR(VLOOKUP($H12,'Rates & Settings'!$A$9:$B$21,2,FALSE)*$I12,0)+$J12,"") | L12: =IF($A12="Header",$B12,IF($A12="Item",IFERROR(INDEX($B$12:$B12,MATCH(2,1/($A$12:$A12="Header"),1)),""),"")) -> Blueprint Strategy
A13: Item | B13: Project setup, brief documents, schedule and client material requests | C13: =IF($A13="Header",SUMIFS($K$12:$K$78,$L$12:$L$78,$L13),"") | D13: Project Management | E13: 4 | K13: =IF($A13="Item",IFERROR(VLOOKUP($D13,'Rates & Settings'!$A$9:$B$21,2,FALSE)*$E13,0)+IFERROR(VLOOKUP($F13,'Rates & Settings'!$A$9:$B$21,2,FALSE)*$G13,0)+IFERROR(VLOOKUP($H13,'Rates & Settings'!$A$9:$B$21,2,FALSE)*$I13,0)+$J13,"") -> 630 | L13: =IF($A13="Header",$B13,IF($A13="Item",IFERROR(INDEX($B$12:$B13,MATCH(2,1/($A$12:$A13="Header"),1)),""),"")) -> Blueprint Strategy
A14: Item | B14: Client and Mettro team kickoff meeting | C14: =IF($A14="Header",SUMIFS($K$12:$K$78,$L$12:$L$78,$L14),"") | D14: Project Management | E14: 2 | K14: =IF($A14="Item",IFERROR(VLOOKUP($D14,'Rates & Settings'!$A$9:$B$21,2,FALSE)*$E14,0)+IFERROR(VLOOKUP($F14,'Rates & Settings'!$A$9:$B$21,2,FALSE)*$G14,0)+IFERROR(VLOOKUP($H14,'Rates & Settings'!$A$9:$B$21,2,FALSE)*$I14,0)+$J14,"") -> 0 | L14: =IF($A14="Header",$B14,IF($A14="Item",IFERROR(INDEX($B$12:$B14,MATCH(2,1/($A$12:$A14="Header"),1)),""),"")) -> Blueprint Strategy
A15: Item | B15: Review of existing Swimming NSW sites, content and asset audit across two sites | C15: =IF($A15="Header",SUMIFS($K$12:$K$78,$L$12:$L$78,$L15),"") | D15: Strategy | E15: 4 | K15: =IF($A15="Item",IFERROR(VLOOKUP($D15,'Rates & Settings'!$A$9:$B$21,2,FALSE)*$E15,0)+IFERROR(VLOOKUP($F15,'Rates & Settings'!$A$9:$B$21,2,FALSE)*$G15,0)+IFERROR(VLOOKUP($H15,'Rates & Settings'!$A$9:$B$21,2,FALSE)*$I15,0)+$J15,"") -> 0 | L15: =IF($A15="Header",$B15,IF($A15="Item",IFERROR(INDEX($B$12:$B15,MATCH(2,1/($A$12:$A15="Header"),1)),""),"")) -> Blueprint Strategy
A16: Item | B16: Content architecture, CPT field definitions, component and template map | C16: =IF($A16="Header",SUMIFS($K$12:$K$78,$L$12:$L$78,$L16),"") | D16: Strategy | E16: 8 | K16: =IF($A16="Item",IFERROR(VLOOKUP($D16,'Rates & Settings'!$A$9:$B$21,2,FALSE)*$E16,0)+IFERROR(VLOOKUP($F16,'Rates & Settings'!$A$9:$B$21,2,FALSE)*$G16,0)+IFERROR(VLOOKUP($H16,'Rates & Settings'!$A$9:$B$21,2,FALSE)*$I16,0)+$J16,"") -> 0 | L16: =IF($A16="Header",$B16,IF($A16="Item",IFERROR(INDEX($B$12:$B16,MATCH(2,1/($A$12:$A16="Header"),1)),""),"")) -> Blueprint Strategy
A17: Item | B17: Blueprint Strategy document | C17: =IF($A17="Header",SUMIFS($K$12:$K$78,$L$12:$L$78,$L17),"") | D17: Strategy | E17: 3 | K17: =IF($A17="Item",IFERROR(VLOOKUP($D17,'Rates & Settings'!$A$9:$B$21,2,FALSE)*$E17,0)+IFERROR(VLOOKUP($F17,'Rates & Settings'!$A$9:$B$21,2,FALSE)*$G17,0)+IFERROR(VLOOKUP($H17,'Rates & Settings'!$A$9:$B$21,2,FALSE)*$I17,0)+$J17,"") -> 0 | L17: =IF($A17="Header",$B17,IF($A17="Item",IFERROR(INDEX($B$12:$B17,MATCH(2,1/($A$12:$A17="Header"),1)),""),"")) -> Blueprint Strategy
A18: Item | B18: Technical framework and plugin recommendations | C18: =IF($A18="Header",SUMIFS($K$12:$K$78,$L$12:$L$78,$L18),"") | D18: Strategy | E18: 2 | K18: =IF($A18="Item",IFERROR(VLOOKUP($D18,'Rates & Settings'!$A$9:$B$21,2,FALSE)*$E18,0)+IFERROR(VLOOKUP($F18,'Rates & Settings'!$A$9:$B$21,2,FALSE)*$G18,0)+IFERROR(VLOOKUP($H18,'Rates & Settings'!$A$9:$B$21,2,FALSE)*$I18,0)+$J18,"") -> 0 | L18: =IF($A18="Header",$B18,IF($A18="Item",IFERROR(INDEX($B$12:$B18,MATCH(2,1/($A$12:$A18="Header"),1)),""),"")) -> Blueprint Strategy
A19: Item | B19: Client sign-off and amendments | C19: =IF($A19="Header",SUMIFS($K$12:$K$78,$L$12:$L$78,$L19),"") | D19: Project Management | E19: 2 | K19: =IF($A19="Item",IFERROR(VLOOKUP($D19,'Rates & Settings'!$A$9:$B$21,2,FALSE)*$E19,0)+IFERROR(VLOOKUP($F19,'Rates & Settings'!$A$9:$B$21,2,FALSE)*$G19,0)+IFERROR(VLOOKUP($H19,'Rates & Settings'!$A$9:$B$21,2,FALSE)*$I19,0)+$J19,"") -> 0 | L19: =IF($A19="Header",$B19,IF($A19="Item",IFERROR(INDEX($B$12:$B19,MATCH(2,1/($A$12:$A19="Header"),1)),""),"")) -> Blueprint Strategy | O19: =(4*270)+(4*230) -> 2000
A20: Spacer | C20: =IF($A20="Header",SUMIFS($K$12:$K$78,$L$12:$L$78,$L20),"") | K20: =IF($A20="Item",IFERROR(VLOOKUP($D20,'Rates & Settings'!$A$9:$B$21,2,FALSE)*$E20,0)+IFERROR(VLOOKUP($F20,'Rates & Settings'!$A$9:$B$21,2,FALSE)*$G20,0)+IFERROR(VLOOKUP($H20,'Rates & Settings'!$A$9:$B$21,2,FALSE)*$I20,0)+$J20,"") | L20: =IF($A20="Header",$B20,IF($A20="Item",IFERROR(INDEX($B$12:$B20,MATCH(2,1/($A$12:$A20="Header"),1)),""),""))
A21: Header | B21: Design: Artwork Adaptation | C21: =IF($A21="Header",SUMIFS($K$12:$K$78,$L$12:$L$78,$L21),"") -> 0 | K21: =IF($A21="Item",IFERROR(VLOOKUP($D21,'Rates & Settings'!$A$9:$B$21,2,FALSE)*$E21,0)+IFERROR(VLOOKUP($F21,'Rates & Settings'!$A$9:$B$21,2,FALSE)*$G21,0)+IFERROR(VLOOKUP($H21,'Rates & Settings'!$A$9:$B$21,2,FALSE)*$I21,0)+$J21,"") | L21: =IF($A21="Header",$B21,IF($A21="Item",IFERROR(INDEX($B$12:$B21,MATCH(2,1/($A$12:$A21="Header"),1)),""),"")) -> Design
A22: Item | B22: Homepage design adaptation | C22: =IF($A22="Header",SUMIFS($K$12:$K$78,$L$12:$L$78,$L22),"") | D22: Design | E22: 10 | K22: =IF($A22="Item",IFERROR(VLOOKUP($D22,'Rates & Settings'!$A$9:$B$21,2,FALSE)*$E22,0)+IFERROR(VLOOKUP($F22,'Rates & Settings'!$A$9:$B$21,2,FALSE)*$G22,0)+IFERROR(VLOOKUP($H22,'Rates & Settings'!$A$9:$B$21,2,FALSE)*$I22,0)+$J22,"") -> 0 | L22: =IF($A22="Header",$B22,IF($A22="Item",IFERROR(INDEX($B$12:$B22,MATCH(2,1/($A$12:$A22="Header"),1)),""),"")) -> Design
A23: Item | B23: Mega menu and primary navigation design | C23: =IF($A23="Header",SUMIFS($K$12:$K$78,$L$12:$L$78,$L23),"") | D23: Design | E23: 3 | K23: =IF($A23="Item",IFERROR(VLOOKUP($D23,'Rates & Settings'!$A$9:$B$21,2,FALSE)*$E23,0)+IFERROR(VLOOKUP($F23,'Rates & Settings'!$A$9:$B$21,2,FALSE)*$G23,0)+IFERROR(VLOOKUP($H23,'Rates & Settings'!$A$9:$B$21,2,FALSE)*$I23,0)+$J23,"") -> 0 | L23: =IF($A23="Header",$B23,IF($A23="Item",IFERROR(INDEX($B$12:$B23,MATCH(2,1/($A$12:$A23="Header"),1)),""),"")) -> Design
A24: Item | B24: Interior and standard content page template | C24: =IF($A24="Header",SUMIFS($K$12:$K$78,$L$12:$L$78,$L24),"") | D24: Design | E24: 5 | K24: =IF($A24="Item",IFERROR(VLOOKUP($D24,'Rates & Settings'!$A$9:$B$21,2,FALSE)*$E24,0)+IFERROR(VLOOKUP($F24,'Rates & Settings'!$A$9:$B$21,2,FALSE)*$G24,0)+IFERROR(VLOOKUP($H24,'Rates & Settings'!$A$9:$B$21,2,FALSE)*$I24,0)+$J24,"") -> 0 | L24: =IF($A24="Header",$B24,IF($A24="Item",IFERROR(INDEX($B$12:$B24,MATCH(2,1/($A$12:$A24="Header"),1)),""),"")) -> Design
A25: Item | B25: News listing and news article detail page | C25: =IF($A25="Header",SUMIFS($K$12:$K$78,$L$12:$L$78,$L25),"") | D25: Design | E25: 5 | K25: =IF($A25="Item",IFERROR(VLOOKUP($D25,'Rates & Settings'!$A$9:$B$21,2,FALSE)*$E25,0)+IFERROR(VLOOKUP($F25,'Rates & Settings'!$A$9:$B$21,2,FALSE)*$G25,0)+IFERROR(VLOOKUP($H25,'Rates & Settings'!$A$9:$B$21,2,FALSE)*$I25,0)+$J25,"") -> 0 | L25: =IF($A25="Header",$B25,IF($A25="Item",IFERROR(INDEX($B$12:$B25,MATCH(2,1/($A$12:$A25="Header"),1)),""),"")) -> Design
A26: Item | B26: Events listing (grid, list and monthly calendar views) and event detail page | C26: =IF($A26="Header",SUMIFS($K$12:$K$78,$L$12:$L$78,$L26),"") | D26: Design | E26: 7 | K26: =IF($A26="Item",IFERROR(VLOOKUP($D26,'Rates & Settings'!$A$9:$B$21,2,FALSE)*$E26,0)+IFERROR(VLOOKUP($F26,'Rates & Settings'!$A$9:$B$21,2,FALSE)*$G26,0)+IFERROR(VLOOKUP($H26,'Rates & Settings'!$A$9:$B$21,2,FALSE)*$I26,0)+$J26,"") -> 0 | L26: =IF($A26="Header",$B26,IF($A26="Item",IFERROR(INDEX($B$12:$B26,MATCH(2,1/($A$12:$A26="Header"),1)),""),"")) -> Design
A27: Item | B27: Resource Hub listing and resource detail page | C27: =IF($A27="Header",SUMIFS($K$12:$K$78,$L$12:$L$78,$L27),"") | D27: Design | E27: 6 | K27: =IF($A27="Item",IFERROR(VLOOKUP($D27,'Rates & Settings'!$A$9:$B$21,2,FALSE)*$E27,0)+IFERROR(VLOOKUP($F27,'Rates & Settings'!$A$9:$B$21,2,FALSE)*$G27,0)+IFERROR(VLOOKUP($H27,'Rates & Settings'!$A$9:$B$21,2,FALSE)*$I27,0)+$J27,"") -> 0 | L27: =IF($A27="Header",$B27,IF($A27="Item",IFERROR(INDEX($B$12:$B27,MATCH(2,1/($A$12:$A27="Header"),1)),""),"")) -> Design
A28: Item | B28: Sponsors and partners section | C28: =IF($A28="Header",SUMIFS($K$12:$K$78,$L$12:$L$78,$L28),"") | D28: Design | E28: 3 | K28: =IF($A28="Item",IFERROR(VLOOKUP($D28,'Rates & Settings'!$A$9:$B$21,2,FALSE)*$E28,0)+IFERROR(VLOOKUP($F28,'Rates & Settings'!$A$9:$B$21,2,FALSE)*$G28,0)+IFERROR(VLOOKUP($H28,'Rates & Settings'!$A$9:$B$21,2,FALSE)*$I28,0)+$J28,"") -> 0 | L28: =IF($A28="Header",$B28,IF($A28="Item",IFERROR(INDEX($B$12:$B28,MATCH(2,1/($A$12:$A28="Header"),1)),""),"")) -> Design
A29: Item | B29: Additional page templates (est. 3, confirmed at Blueprint stage) | C29: =IF($A29="Header",SUMIFS($K$12:$K$78,$L$12:$L$78,$L29),"") | D29: Design | E29: 7 | K29: =IF($A29="Item",IFERROR(VLOOKUP($D29,'Rates & Settings'!$A$9:$B$21,2,FALSE)*$E29,0)+IFERROR(VLOOKUP($F29,'Rates & Settings'!$A$9:$B$21,2,FALSE)*$G29,0)+IFERROR(VLOOKUP($H29,'Rates & Settings'!$A$9:$B$21,2,FALSE)*$I29,0)+$J29,"") -> 0 | L29: =IF($A29="Header",$B29,IF($A29="Item",IFERROR(INDEX($B$12:$B29,MATCH(2,1/($A$12:$A29="Header"),1)),""),"")) -> Design
A30: Item | C30: =IF($A30="Header",SUMIFS($K$12:$K$78,$L$12:$L$78,$L30),"") | K30: =IF($A30="Item",IFERROR(VLOOKUP($D30,'Rates & Settings'!$A$9:$B$21,2,FALSE)*$E30,0)+IFERROR(VLOOKUP($F30,'Rates & Settings'!$A$9:$B$21,2,FALSE)*$G30,0)+IFERROR(VLOOKUP($H30,'Rates & Settings'!$A$9:$B$21,2,FALSE)*$I30,0)+$J30,"") -> 0 | L30: =IF($A30="Header",$B30,IF($A30="Item",IFERROR(INDEX($B$12:$B30,MATCH(2,1/($A$12:$A30="Header"),1)),""),"")) -> Design
A31: Item | C31: =IF($A31="Header",SUMIFS($K$12:$K$78,$L$12:$L$78,$L31),"") | K31: =IF($A31="Item",IFERROR(VLOOKUP($D31,'Rates & Settings'!$A$9:$B$21,2,FALSE)*$E31,0)+IFERROR(VLOOKUP($F31,'Rates & Settings'!$A$9:$B$21,2,FALSE)*$G31,0)+IFERROR(VLOOKUP($H31,'Rates & Settings'!$A$9:$B$21,2,FALSE)*$I31,0)+$J31,"") -> 0 | L31: =IF($A31="Header",$B31,IF($A31="Item",IFERROR(INDEX($B$12:$B31,MATCH(2,1/($A$12:$A31="Header"),1)),""),"")) -> Design
A32: Spacer | C32: =IF($A32="Header",SUMIFS($K$12:$K$78,$L$12:$L$78,$L32),"") | K32: =IF($A32="Item",IFERROR(VLOOKUP($D32,'Rates & Settings'!$A$9:$B$21,2,FALSE)*$E32,0)+IFERROR(VLOOKUP($F32,'Rates & Settings'!$A$9:$B$21,2,FALSE)*$G32,0)+IFERROR(VLOOKUP($H32,'Rates & Settings'!$A$9:$B$21,2,FALSE)*$I32,0)+$J32,"") | L32: =IF($A32="Header",$B32,IF($A32="Item",IFERROR(INDEX($B$12:$B32,MATCH(2,1/($A$12:$A32="Header"),1)),""),""))
A33: Header | B33: Development | C33: =IF($A33="Header",SUMIFS($K$12:$K$78,$L$12:$L$78,$L33),"") -> 0 | K33: =IF($A33="Item",IFERROR(VLOOKUP($D33,'Rates & Settings'!$A$9:$B$21,2,FALSE)*$E33,0)+IFERROR(VLOOKUP($F33,'Rates & Settings'!$A$9:$B$21,2,FALSE)*$G33,0)+IFERROR(VLOOKUP($H33,'Rates & Settings'!$A$9:$B$21,2,FALSE)*$I33,0)+$J33,"") | L33: =IF($A33="Header",$B33,IF($A33="Item",IFERROR(INDEX($B$12:$B33,MATCH(2,1/($A$12:$A33="Header"),1)),""),"")) -> Development
A34: Item | B34: WordPress CMS environment setup | C34: =IF($A34="Header",SUMIFS($K$12:$K$78,$L$12:$L$78,$L34),"") | D34: Development | E34: 2 | K34: =IF($A34="Item",IFERROR(VLOOKUP($D34,'Rates & Settings'!$A$9:$B$21,2,FALSE)*$E34,0)+IFERROR(VLOOKUP($F34,'Rates & Settings'!$A$9:$B$21,2,FALSE)*$G34,0)+IFERROR(VLOOKUP($H34,'Rates & Settings'!$A$9:$B$21,2,FALSE)*$I34,0)+$J34,"") -> 0 | L34: =IF($A34="Header",$B34,IF($A34="Item",IFERROR(INDEX($B$12:$B34,MATCH(2,1/($A$12:$A34="Header"),1)),""),"")) -> Development
A35: Item | B35: GreyboxPro theme and global style engine | C35: =IF($A35="Header",SUMIFS($K$12:$K$78,$L$12:$L$78,$L35),"") | D35: Development | E35: 6 | K35: =IF($A35="Item",IFERROR(VLOOKUP($D35,'Rates & Settings'!$A$9:$B$21,2,FALSE)*$E35,0)+IFERROR(VLOOKUP($F35,'Rates & Settings'!$A$9:$B$21,2,FALSE)*$G35,0)+IFERROR(VLOOKUP($H35,'Rates & Settings'!$A$9:$B$21,2,FALSE)*$I35,0)+$J35,"") -> 0 | L35: =IF($A35="Header",$B35,IF($A35="Item",IFERROR(INDEX($B$12:$B35,MATCH(2,1/($A$12:$A35="Header"),1)),""),"")) -> Development
A36: Item | B36: Brand configuration: CSS custom properties, colours and typography | C36: =IF($A36="Header",SUMIFS($K$12:$K$78,$L$12:$L$78,$L36),"") | D36: Development | E36: 4 | K36: =IF($A36="Item",IFERROR(VLOOKUP($D36,'Rates & Settings'!$A$9:$B$21,2,FALSE)*$E36,0)+IFERROR(VLOOKUP($F36,'Rates & Settings'!$A$9:$B$21,2,FALSE)*$G36,0)+IFERROR(VLOOKUP($H36,'Rates & Settings'!$A$9:$B$21,2,FALSE)*$I36,0)+$J36,"") -> 0 | L36: =IF($A36="Header",$B36,IF($A36="Item",IFERROR(INDEX($B$12:$B36,MATCH(2,1/($A$12:$A36="Header"),1)),""),"")) -> Development
A37: Item | B37: Mega menu and primary navigation build | C37: =IF($A37="Header",SUMIFS($K$12:$K$78,$L$12:$L$78,$L37),"") | D37: Development | E37: 8 | K37: =IF($A37="Item",IFERROR(VLOOKUP($D37,'Rates & Settings'!$A$9:$B$21,2,FALSE)*$E37,0)+IFERROR(VLOOKUP($F37,'Rates & Settings'!$A$9:$B$21,2,FALSE)*$G37,0)+IFERROR(VLOOKUP($H37,'Rates & Settings'!$A$9:$B$21,2,FALSE)*$I37,0)+$J37,"") -> 0 | L37: =IF($A37="Header",$B37,IF($A37="Item",IFERROR(INDEX($B$12:$B37,MATCH(2,1/($A$12:$A37="Header"),1)),""),"")) -> Development
A38: Item | B38: Homepage build | C38: =IF($A38="Header",SUMIFS($K$12:$K$78,$L$12:$L$78,$L38),"") | D38: Development | E38: 10 | K38: =IF($A38="Item",IFERROR(VLOOKUP($D38,'Rates & Settings'!$A$9:$B$21,2,FALSE)*$E38,0)+IFERROR(VLOOKUP($F38,'Rates & Settings'!$A$9:$B$21,2,FALSE)*$G38,0)+IFERROR(VLOOKUP($H38,'Rates & Settings'!$A$9:$B$21,2,FALSE)*$I38,0)+$J38,"") -> 0 | L38: =IF($A38="Header",$B38,IF($A38="Item",IFERROR(INDEX($B$12:$B38,MATCH(2,1/($A$12:$A38="Header"),1)),""),"")) -> Development
A39: Item | B39: Interior and standard page template build | C39: =IF($A39="Header",SUMIFS($K$12:$K$78,$L$12:$L$78,$L39),"") | D39: Development | E39: 6 | K39: =IF($A39="Item",IFERROR(VLOOKUP($D39,'Rates & Settings'!$A$9:$B$21,2,FALSE)*$E39,0)+IFERROR(VLOOKUP($F39,'Rates & Settings'!$A$9:$B$21,2,FALSE)*$G39,0)+IFERROR(VLOOKUP($H39,'Rates & Settings'!$A$9:$B$21,2,FALSE)*$I39,0)+$J39,"") -> 0 | L39: =IF($A39="Header",$B39,IF($A39="Item",IFERROR(INDEX($B$12:$B39,MATCH(2,1/($A$12:$A39="Header"),1)),""),"")) -> Development
A40: Item | B40: Contact form (Gravity Forms) | C40: =IF($A40="Header",SUMIFS($K$12:$K$78,$L$12:$L$78,$L40),"") | D40: Development | E40: 3 | K40: =IF($A40="Item",IFERROR(VLOOKUP($D40,'Rates & Settings'!$A$9:$B$21,2,FALSE)*$E40,0)+IFERROR(VLOOKUP($F40,'Rates & Settings'!$A$9:$B$21,2,FALSE)*$G40,0)+IFERROR(VLOOKUP($H40,'Rates & Settings'!$A$9:$B$21,2,FALSE)*$I40,0)+$J40,"") -> 0 | L40: =IF($A40="Header",$B40,IF($A40="Item",IFERROR(INDEX($B$12:$B40,MATCH(2,1/($A$12:$A40="Header"),1)),""),"")) -> Development
A41: Item | B41: Site search configuration | C41: =IF($A41="Header",SUMIFS($K$12:$K$78,$L$12:$L$78,$L41),"") | D41: Development | E41: 3 | K41: =IF($A41="Item",IFERROR(VLOOKUP($D41,'Rates & Settings'!$A$9:$B$21,2,FALSE)*$E41,0)+IFERROR(VLOOKUP($F41,'Rates & Settings'!$A$9:$B$21,2,FALSE)*$G41,0)+IFERROR(VLOOKUP($H41,'Rates & Settings'!$A$9:$B$21,2,FALSE)*$I41,0)+$J41,"") -> 0 | L41: =IF($A41="Header",$B41,IF($A41="Item",IFERROR(INDEX($B$12:$B41,MATCH(2,1/($A$12:$A41="Header"),1)),""),"")) -> Development
A42: Item | B42: Google Analytics 4 and Google Search Console setup | C42: =IF($A42="Header",SUMIFS($K$12:$K$78,$L$12:$L$78,$L42),"") | D42: Development | E42: 2 | K42: =IF($A42="Item",IFERROR(VLOOKUP($D42,'Rates & Settings'!$A$9:$B$21,2,FALSE)*$E42,0)+IFERROR(VLOOKUP($F42,'Rates & Settings'!$A$9:$B$21,2,FALSE)*$G42,0)+IFERROR(VLOOKUP($H42,'Rates & Settings'!$A$9:$B$21,2,FALSE)*$I42,0)+$J42,"") -> 0 | L42: =IF($A42="Header",$B42,IF($A42="Item",IFERROR(INDEX($B$12:$B42,MATCH(2,1/($A$12:$A42="Header"),1)),""),"")) -> Development
A43: Item | B43: reCAPTCHA integration | C43: =IF($A43="Header",SUMIFS($K$12:$K$78,$L$12:$L$78,$L43),"") | D43: Development | E43: 2 | K43: =IF($A43="Item",IFERROR(VLOOKUP($D43,'Rates & Settings'!$A$9:$B$21,2,FALSE)*$E43,0)+IFERROR(VLOOKUP($F43,'Rates & Settings'!$A$9:$B$21,2,FALSE)*$G43,0)+IFERROR(VLOOKUP($H43,'Rates & Settings'!$A$9:$B$21,2,FALSE)*$I43,0)+$J43,"") -> 0 | L43: =IF($A43="Header",$B43,IF($A43="Item",IFERROR(INDEX($B$12:$B43,MATCH(2,1/($A$12:$A43="Header"),1)),""),"")) -> Development
A44: Item | B44: Events Custom Post Type setup | C44: =IF($A44="Header",SUMIFS($K$12:$K$78,$L$12:$L$78,$L44),"") | D44: Development | E44: 4 | K44: =IF($A44="Item",IFERROR(VLOOKUP($D44,'Rates & Settings'!$A$9:$B$21,2,FALSE)*$E44,0)+IFERROR(VLOOKUP($F44,'Rates & Settings'!$A$9:$B$21,2,FALSE)*$G44,0)+IFERROR(VLOOKUP($H44,'Rates & Settings'!$A$9:$B$21,2,FALSE)*$I44,0)+$J44,"") -> 0 | L44: =IF($A44="Header",$B44,IF($A44="Item",IFERROR(INDEX($B$12:$B44,MATCH(2,1/($A$12:$A44="Header"),1)),""),"")) -> Development
A45: Item | B45: WordPress calendar plugin installation and configuration | C45: =IF($A45="Header",SUMIFS($K$12:$K$78,$L$12:$L$78,$L45),"") | D45: Development | E45: 4 | K45: =IF($A45="Item",IFERROR(VLOOKUP($D45,'Rates & Settings'!$A$9:$B$21,2,FALSE)*$E45,0)+IFERROR(VLOOKUP($F45,'Rates & Settings'!$A$9:$B$21,2,FALSE)*$G45,0)+IFERROR(VLOOKUP($H45,'Rates & Settings'!$A$9:$B$21,2,FALSE)*$I45,0)+$J45,"") -> 0 | L45: =IF($A45="Header",$B45,IF($A45="Item",IFERROR(INDEX($B$12:$B45,MATCH(2,1/($A$12:$A45="Header"),1)),""),"")) -> Development
... A54: Item | B54: OneDrive document library: linking from relevant pages | C54: =IF($A54="Header",SUMIFS($K$12:$K$78,$L$12:$L$78,$L54),"") | D54: Integration & Technical | E54: 4 | K54: =IF($A54="Item",IFERROR(VLOOKUP($D54,'Rates & Settings'!$A$9:$B$21,2,FALSE)*$E54,0)+IFERROR(VLOOKUP($F54,'Rates & Settings'!$A$9:$B$21,2,FALSE)*$G54,0)+IFERROR(VLOOKUP($H54,'Rates & Settings'!$A$9:$B$21,2,FALSE)*$I54,0)+$J54,"") -> 0 | L54: =IF($A54="Header",$B54,IF($A54="Item",IFERROR(INDEX($B$12:$B54,MATCH(2,1/($A$12:$A54="Header"),1)),""),"")) -> Development
A55: Item | C55: =IF($A55="Header",SUMIFS($K$12:$K$78,$L$12:$L$78,$L55),"") | K55: =IF($A55="Item",IFERROR(VLOOKUP($D55,'Rates & Settings'!$A$9:$B$21,2,FALSE)*$E55,0)+IFERROR(VLOOKUP($F55,'Rates & Settings'!$A$9:$B$21,2,FALSE)*$G55,0)+IFERROR(VLOOKUP($H55,'Rates & Settings'!$A$9:$B$21,2,FALSE)*$I55,0)+$J55,"") -> 0 | L55: =IF($A55="Header",$B55,IF($A55="Item",IFERROR(INDEX($B$12:$B55,MATCH(2,1/($A$12:$A55="Header"),1)),""),"")) -> Development
A56: Item | C56: =IF($A56="Header",SUMIFS($K$12:$K$78,$L$12:$L$78,$L56),"") | K56: =IF($A56="Item",IFERROR(VLOOKUP($D56,'Rates & Settings'!$A$9:$B$21,2,FALSE)*$E56,0)+IFERROR(VLOOKUP($F56,'Rates & Settings'!$A$9:$B$21,2,FALSE)*$G56,0)+IFERROR(VLOOKUP($H56,'Rates & Settings'!$A$9:$B$21,2,FALSE)*$I56,0)+$J56,"") -> 0 | L56: =IF($A56="Header",$B56,IF($A56="Item",IFERROR(INDEX($B$12:$B56,MATCH(2,1/($A$12:$A56="Header"),1)),""),"")) -> Development
A57: Item | C57: =IF($A57="Header",SUMIFS($K$12:$K$78,$L$12:$L$78,$L57),"") | K57: =IF($A57="Item",IFERROR(VLOOKUP($D57,'Rates & Settings'!$A$9:$B$21,2,FALSE)*$E57,0)+IFERROR(VLOOKUP($F57,'Rates & Settings'!$A$9:$B$21,2,FALSE)*$G57,0)+IFERROR(VLOOKUP($H57,'Rates & Settings'!$A$9:$B$21,2,FALSE)*$I57,0)+$J57,"") -> 0 | L57: =IF($A57="Header",$B57,IF($A57="Item",IFERROR(INDEX($B$12:$B57,MATCH(2,1/($A$12:$A57="Header"),1)),""),"")) -> Development
A58: Item | C58: =IF($A58="Header",SUMIFS($K$12:$K$78,$L$12:$L$78,$L58),"") | K58: =IF($A58="Item",IFERROR(VLOOKUP($D58,'Rates & Settings'!$A$9:$B$21,2,FALSE)*$E58,0)+IFERROR(VLOOKUP($F58,'Rates & Settings'!$A$9:$B$21,2,FALSE)*$G58,0)+IFERROR(VLOOKUP($H58,'Rates & Settings'!$A$9:$B$21,2,FALSE)*$I58,0)+$J58,"") -> 0 | L58: =IF($A58="Header",$B58,IF($A58="Item",IFERROR(INDEX($B$12:$B58,MATCH(2,1/($A$12:$A58="Header"),1)),""),"")) -> Development
A59: Item | C59: =IF($A59="Header",SUMIFS($K$12:$K$78,$L$12:$L$78,$L59),"") | K59: =IF($A59="Item",IFERROR(VLOOKUP($D59,'Rates & Settings'!$A$9:$B$21,2,FALSE)*$E59,0)+IFERROR(VLOOKUP($F59,'Rates & Settings'!$A$9:$B$21,2,FALSE)*$G59,0)+IFERROR(VLOOKUP($H59,'Rates & Settings'!$A$9:$B$21,2,FALSE)*$I59,0)+$J59,"") -> 0 | L59: =IF($A59="Header",$B59,IF($A59="Item",IFERROR(INDEX($B$12:$B59,MATCH(2,1/($A$12:$A59="Header"),1)),""),"")) -> Development
A60: Item | C60: =IF($A60="Header",SUMIFS($K$12:$K$78,$L$12:$L$78,$L60),"") | K60: =IF($A60="Item",IFERROR(VLOOKUP($D60,'Rates & Settings'!$A$9:$B$21,2,FALSE)*$E60,0)+IFERROR(VLOOKUP($F60,'Rates & Settings'!$A$9:$B$21,2,FALSE)*$G60,0)+IFERROR(VLOOKUP($H60,'Rates & Settings'!$A$9:$B$21,2,FALSE)*$I60,0)+$J60,"") -> 0 | L60: =IF($A60="Header",$B60,IF($A60="Item",IFERROR(INDEX($B$12:$B60,MATCH(2,1/($A$12:$A60="Header"),1)),""),"")) -> Development
A61: Item | C61: =IF($A61="Header",SUMIFS($K$12:$K$78,$L$12:$L$78,$L61),"") | K61: =IF($A61="Item",IFERROR(VLOOKUP($D61,'Rates & Settings'!$A$9:$B$21,2,FALSE)*$E61,0)+IFERROR(VLOOKUP($F61,'Rates & Settings'!$A$9:$B$21,2,FALSE)*$G61,0)+IFERROR(VLOOKUP($H61,'Rates & Settings'!$A$9:$B$21,2,FALSE)*$I61,0)+$J61,"") -> 0 | L61: =IF($A61="Header",$B61,IF($A61="Item",IFERROR(INDEX($B$12:$B61,MATCH(2,1/($A$12:$A61="Header"),1)),""),"")) -> Development
A62: Item | C62: =IF($A62="Header",SUMIFS($K$12:$K$78,$L$12:$L$78,$L62),"") | K62: =IF($A62="Item",IFERROR(VLOOKUP($D62,'Rates & Settings'!$A$9:$B$21,2,FALSE)*$E62,0)+IFERROR(VLOOKUP($F62,'Rates & Settings'!$A$9:$B$21,2,FALSE)*$G62,0)+IFERROR(VLOOKUP($H62,'Rates & Settings'!$A$9:$B$21,2,FALSE)*$I62,0)+$J62,"") -> 0 | L62: =IF($A62="Header",$B62,IF($A62="Item",IFERROR(INDEX($B$12:$B62,MATCH(2,1/($A$12:$A62="Header"),1)),""),"")) -> Development
A63: Spacer | C63: =IF($A63="Header",SUMIFS($K$12:$K$78,$L$12:$L$78,$L63),"") | K63: =IF($A63="Item",IFERROR(VLOOKUP($D63,'Rates & Settings'!$A$9:$B$21,2,FALSE)*$E63,0)+IFERROR(VLOOKUP($F63,'Rates & Settings'!$A$9:$B$21,2,FALSE)*$G63,0)+IFERROR(VLOOKUP($H63,'Rates & Settings'!$A$9:$B$21,2,FALSE)*$I63,0)+$J63,"") | L63: =IF($A63="Header",$B63,IF($A63="Item",IFERROR(INDEX($B$12:$B63,MATCH(2,1/($A$12:$A63="Header"),1)),""),""))
A64: Header | B64: Content and Training | C64: =IF($A64="Header",SUMIFS($K$12:$K$78,$L$12:$L$78,$L64),"") -> 0 | K64: =IF($A64="Item",IFERROR(VLOOKUP($D64,'Rates & Settings'!$A$9:$B$21,2,FALSE)*$E64,0)+IFERROR(VLOOKUP($F64,'Rates & Settings'!$A$9:$B$21,2,FALSE)*$G64,0)+IFERROR(VLOOKUP($H64,'Rates & Settings'!$A$9:$B$21,2,FALSE)*$I64,0)+$J64,"") | L64: =IF($A64="Header",$B64,IF($A64="Item",IFERROR(INDEX($B$12:$B64,MATCH(2,1/($A$12:$A64="Header"),1)),""),"")) -> Content and Training
A65: Item | B65: Content entry: homepage and interior pages | C65: =IF($A65="Header",SUMIFS($K$12:$K$78,$L$12:$L$78,$L65),"") | D65: Content Entry | E65: 8 | K65: =IF($A65="Item",IFERROR(VLOOKUP($D65,'Rates & Settings'!$A$9:$B$21,2,FALSE)*$E65,0)+IFERROR(VLOOKUP($F65,'Rates & Settings'!$A$9:$B$21,2,FALSE)*$G65,0)+IFERROR(VLOOKUP($H65,'Rates & Settings'!$A$9:$B$21,2,FALSE)*$I65,0)+$J65,"") -> 0 | L65: =IF($A65="Header",$B65,IF($A65="Item",IFERROR(INDEX($B$12:$B65,MATCH(2,1/($A$12:$A65="Header"),1)),""),"")) -> Content and Training
A66: Item | B66: Content entry: news, events and Resource Hub | C66: =IF($A66="Header",SUMIFS($K$12:$K$78,$L$12:$L$78,$L66),"") | D66: Content Entry | E66: 8 | K66: =IF($A66="Item",IFERROR(VLOOKUP($D66,'Rates & Settings'!$A$9:$B$21,2,FALSE)*$E66,0)+IFERROR(VLOOKUP($F66,'Rates & Settings'!$A$9:$B$21,2,FALSE)*$G66,0)+IFERROR(VLOOKUP($H66,'Rates & Settings'!$A$9:$B$21,2,FALSE)*$I66,0)+$J66,"") -> 0 | L66: =IF($A66="Header",$B66,IF($A66="Item",IFERROR(INDEX($B$12:$B66,MATCH(2,1/($A$12:$A66="Header"),1)),""),"")) -> Content and Training
A67: Item | B67: Content entry: sponsors, forms and metadata | C67: =IF($A67="Header",SUMIFS($K$12:$K$78,$L$12:$L$78,$L67),"") | D67: Content Entry | E67: 4 | K67: =IF($A67="Item",IFERROR(VLOOKUP($D67,'Rates & Settings'!$A$9:$B$21,2,FALSE)*$E67,0)+IFERROR(VLOOKUP($F67,'Rates & Settings'!$A$9:$B$21,2,FALSE)*$G67,0)+IFERROR(VLOOKUP($H67,'Rates & Settings'!$A$9:$B$21,2,FALSE)*$I67,0)+$J67,"") -> 0 | L67: =IF($A67="Header",$B67,IF($A67="Item",IFERROR(INDEX($B$12:$B67,MATCH(2,1/($A$12:$A67="Header"),1)),""),"")) -> Content and Training
A68: Item | B68: CMS training session (online or in person) | C68: =IF($A68="Header",SUMIFS($K$12:$K$78,$L$12:$L$78,$L68),"") | D68: Project Management | E68: 3 | K68: =IF($A68="Item",IFERROR(VLOOKUP($D68,'Rates & Settings'!$A$9:$B$21,2,FALSE)*$E68,0)+IFERROR(VLOOKUP($F68,'Rates & Settings'!$A$9:$B$21,2,FALSE)*$G68,0)+IFERROR(VLOOKUP($H68,'Rates & Settings'!$A$9:$B$21,2,FALSE)*$I68,0)+$J68,"") -> 0 | L68: =IF($A68="Header",$B68,IF($A68="Item",IFERROR(INDEX($B$12:$B68,MATCH(2,1/($A$12:$A68="Header"),1)),""),"")) -> Content and Training
A69: Spacer | C69: =IF($A69="Header",SUMIFS($K$12:$K$78,$L$12:$L$78,$L69),"") | K69: =IF($A69="Item",IFERROR(VLOOKUP($D69,'Rates & Settings'!$A$9:$B$21,2,FALSE)*$E69,0)+IFERROR(VLOOKUP($F69,'Rates & Settings'!$A$9:$B$21,2,FALSE)*$G69,0)+IFERROR(VLOOKUP($H69,'Rates & Settings'!$A$9:$B$21,2,FALSE)*$I69,0)+$J69,"") | L69: =IF($A69="Header",$B69,IF($A69="Item",IFERROR(INDEX($B$12:$B69,MATCH(2,1/($A$12:$A69="Header"),1)),""),""))
A70: Header | B70: Golive and Delivery | C70: =IF($A70="Header",SUMIFS($K$12:$K$78,$L$12:$L$78,$L70),"") -> 0 | K70: =IF($A70="Item",IFERROR(VLOOKUP($D70,'Rates & Settings'!$A$9:$B$21,2,FALSE)*$E70,0)+IFERROR(VLOOKUP($F70,'Rates & Settings'!$A$9:$B$21,2,FALSE)*$G70,0)+IFERROR(VLOOKUP($H70,'Rates & Settings'!$A$9:$B$21,2,FALSE)*$I70,0)+$J70,"") | L70: =IF($A70="Header",$B70,IF($A70="Item",IFERROR(INDEX($B$12:$B70,MATCH(2,1/($A$12:$A70="Header"),1)),""),"")) -> Golive and Delivery
A71: Item | B71: Pre-golive QA: cross-browser and device testing | C71: =IF($A71="Header",SUMIFS($K$12:$K$78,$L$12:$L$78,$L71),"") | D71: Quality Assurance | E71: 10 | K71: =IF($A71="Item",IFERROR(VLOOKUP($D71,'Rates & Settings'!$A$9:$B$21,2,FALSE)*$E71,0)+IFERROR(VLOOKUP($F71,'Rates & Settings'!$A$9:$B$21,2,FALSE)*$G71,0)+IFERROR(VLOOKUP($H71,'Rates & Settings'!$A$9:$B$21,2,FALSE)*$I71,0)+$J71,"") -> 0 | L71: =IF($A71="Header",$B71,IF($A71="Item",IFERROR(INDEX($B$12:$B71,MATCH(2,1/($A$12:$A71="Header"),1)),""),"")) -> Golive and Delivery
A72: Item | B72: Forms, integrations and functionality testing | C72: =IF($A72="Header",SUMIFS($K$12:$K$78,$L$12:$L$78,$L72),"") | D72: Quality Assurance | E72: 4 | K72: =IF($A72="Item",IFERROR(VLOOKUP($D72,'Rates & Settings'!$A$9:$B$21,2,FALSE)*$E72,0)+IFERROR(VLOOKUP($F72,'Rates & Settings'!$A$9:$B$21,2,FALSE)*$G72,0)+IFERROR(VLOOKUP($H72,'Rates & Settings'!$A$9:$B$21,2,FALSE)*$I72,0)+$J72,"") -> 0 | L72: =IF($A72="Header",$B72,IF($A72="Item",IFERROR(INDEX($B$12:$B72,MATCH(2,1/($A$12:$A72="Header"),1)),""),"")) -> Golive and Delivery
A73: Item | B73: 301 redirects: consolidating two existing sites into one | C73: =IF($A73="Header",SUMIFS($K$12:$K$78,$L$12:$L$78,$L73),"") | D73: Development | E73: 6 | K73: =IF($A73="Item",IFERROR(VLOOKUP($D73,'Rates & Settings'!$A$9:$B$21,2,FALSE)*$E73,0)+IFERROR(VLOOKUP($F73,'Rates & Settings'!$A$9:$B$21,2,FALSE)*$G73,0)+IFERROR(VLOOKUP($H73,'Rates & Settings'!$A$9:$B$21,2,FALSE)*$I73,0)+$J73,"") -> 0 | L73: =IF($A73="Header",$B73,IF($A73="Item",IFERROR(INDEX($B$12:$B73,MATCH(2,1/($A$12:$A73="Header"),1)),""),"")) -> Golive and Delivery
A74: Item | B74: Golive execution | C74: =IF($A74="Header",SUMIFS($K$12:$K$78,$L$12:$L$78,$L74),"") | D74: Quality Assurance | E74: 2 | K74: =IF($A74="Item",IFERROR(VLOOKUP($D74,'Rates & Settings'!$A$9:$B$21,2,FALSE)*$E74,0)+IFERROR(VLOOKUP($F74,'Rates & Settings'!$A$9:$B$21,2,FALSE)*$G74,0)+IFERROR(VLOOKUP($H74,'Rates & Settings'!$A$9:$B$21,2,FALSE)*$I74,0)+$J74,"") -> 0 | L74: =IF($A74="Header",$B74,IF($A74="Item",IFERROR(INDEX($B$12:$B74,MATCH(2,1/($A$12:$A74="Header"),1)),""),"")) -> Golive and Delivery
A75: Item | B75: Post-golive QA | C75: =IF($A75="Header",SUMIFS($K$12:$K$78,$L$12:$L$78,$L75),"") | D75: Quality Assurance | E75: 4 | K75: =IF($A75="Item",IFERROR(VLOOKUP($D75,'Rates & Settings'!$A$9:$B$21,2,FALSE)*$E75,0)+IFERROR(VLOOKUP($F75,'Rates & Settings'!$A$9:$B$21,2,FALSE)*$G75,0)+IFERROR(VLOOKUP($H75,'Rates & Settings'!$A$9:$B$21,2,FALSE)*$I75,0)+$J75,"") -> 0 | L75: =IF($A75="Header",$B75,IF($A75="Item",IFERROR(INDEX($B$12:$B75,MATCH(2,1/($A$12:$A75="Header"),1)),""),"")) -> Golive and Delivery
A76: Item | B76: Handover documentation pack | C76: =IF($A76="Header",SUMIFS($K$12:$K$78,$L$12:$L$78,$L76),"") | D76: Project Management | E76: 2 | K76: =IF($A76="Item",IFERROR(VLOOKUP($D76,'Rates & Settings'!$A$9:$B$21,2,FALSE)*$E76,0)+IFERROR(VLOOKUP($F76,'Rates & Settings'!$A$9:$B$21,2,FALSE)*$G76,0)+IFERROR(VLOOKUP($H76,'Rates & Settings'!$A$9:$B$21,2,FALSE)*$I76,0)+$J76,"") -> 0 | L76: =IF($A76="Header",$B76,IF($A76="Item",IFERROR(INDEX($B$12:$B76,MATCH(2,1/($A$12:$A76="Header"),1)),""),"")) -> Golive and Delivery
A77: Item | C77: =IF($A77="Header",SUMIFS($K$12:$K$78,$L$12:$L$78,$L77),"") | K77: =IF($A77="Item",IFERROR(VLOOKUP($D77,'Rates & Settings'!$A$9:$B$21,2,FALSE)*$E77,0)+IFERROR(VLOOKUP($F77,'Rates & Settings'!$A$9:$B$21,2,FALSE)*$G77,0)+IFERROR(VLOOKUP($H77,'Rates & Settings'!$A$9:$B$21,2,FALSE)*$I77,0)+$J77,"") -> 0 | L77: =IF($A77="Header",$B77,IF($A77="Item",IFERROR(INDEX($B$12:$B77,MATCH(2,1/($A$12:$A77="Header"),1)),""),"")) -> Golive and Delivery
C78: =IF($A78="Header",SUMIFS($K$12:$K$78,$L$12:$L$78,$L78),"") | K78: =IF($A78="Item",IFERROR(VLOOKUP($D78,'Rates & Settings'!$A$9:$B$21,2,FALSE)*$E78,0)+IFERROR(VLOOKUP($F78,'Rates & Settings'!$A$9:$B$21,2,FALSE)*$G78,0)+IFERROR(VLOOKUP($H78,'Rates & Settings'!$A$9:$B$21,2,FALSE)*$I78,0)+$J78,"") | L78: =IF($A78="Header",$B78,IF($A78="Item",IFERROR(INDEX($B$12:$B78,MATCH(2,1/($A$12:$A78="Header"),1)),""),""))
L79: =IF(A68="Header",B68,IF(A68="Item",IFERROR(LOOKUP(2,1/($A$2:A68="Header"),$B$2:B68),""),""))
B80: SUBTOTAL | C80: =SUMIF(A:A,"Header",C:C)*(1+$G$4)*(1-$G$5) -> 630 | L80: =IF(A70="Header",B70,IF(A70="Item",IFERROR(LOOKUP(2,1/($A$2:A70="Header"),$B$2:B70),""),"")) -> Golive and Delivery
B81: GST | C81: =C80*'Rates & Settings'!B3 -> 63 | L81: =IF(A71="Header",B71,IF(A71="Item",IFERROR(LOOKUP(2,1/($A$2:A71="Header"),$B$2:B71),""),""))
B82: TOTAL INC GST | C82: =C80+C81 -> 693 | L82: =IF(A72="Header",B72,IF(A72="Item",IFERROR(LOOKUP(2,1/($A$2:A72="Header"),$B$2:B72),""),""))
L83: =IF(A72="Header",B72,IF(A72="Item",IFERROR(LOOKUP(2,1/($A$2:A72="Header"),$B$2:B72),""),""))
B85: Approximate annual plugin licensing per year (paid directly by client) | C85: 2000 | L85: {=IF($A85="Header",$B85,IF($A85="Item",IFERROR(INDEX($B$12:$B85,MATCH(2,1/($A$12:$A85="Header"),1)),""),""))}
B86: *Includes Gravity Forms, calendar plugin. WP Engine hosting to be quoted separately. To be confirmed at Blueprint stage. | L86: =IF(A76="Header",B76,IF(A76="Item",IFERROR(LOOKUP(2,1/($A$2:A76="Header"),$B$2:B76),""),""))
L87: {=IF($A87="Header",$B87,IF($A87="Item",IFERROR(INDEX($B$12:$B87,MATCH(2,1/($A$12:$A87="Header"),1)),""),""))}
B88: Optional Add-Ons (ex GST, not included in base estimate above) | L88: {=IF($A88="Header",#REF!,IF($A88="Item",IFERROR(INDEX($B$12:$B87,MATCH(2,1/($A$12:$A88="Header"),1)),""),""))}
B89: Option A: News Article Migration (800+ articles, Drupal to WordPress): data mapping, bulk import and post-import QA | C89: 5260 | L89: =IF(A80="Header",B80,IF(A80="Item",IFERROR(LOOKUP(2,1/($A$2:A80="Header"),$B$2:B80),""),""))
B90: Option B: Standard Content Page Migration (export/import from existing Drupal site) — content audit, import setup, post-migration QA | C90: 2480 | L90: =IF(A80="Header",B80,IF(A80="Item",IFERROR(LOOKUP(2,1/($A$2:A80="Header"),$B$2:B80),""),""))
B91: All option prices are ex GST. Contingency not applied to optional add-ons. | L91: {=IF($A91="Header",$B90,IF($A91="Item",IFERROR(INDEX($B$12:$B90,MATCH(2,1/($A$12:$A91="Header"),1)),""),""))}
L92: {=IF($A92="Header",$B92,IF($A92="Item",IFERROR(INDEX($B$12:$B92,MATCH(2,1/($A$12:$A92="Header"),1)),""),""))}
L93: =IF(A85="Header",B85,IF(A85="Item",IFERROR(LOOKUP(2,1/($A$2:A85="Header"),$B$2:B85),""),""))
L94: =IF(A83="Header",B83,IF(A83="Item",IFERROR(LOOKUP(2,1/($A$2:A83="Header"),$B$2:B83),""),""))
L95: =IF(A85="Header",B85,IF(A85="Item",IFERROR(LOOKUP(2,1/($A$2:A85="Header"),$B$2:B85),""),""))
L96: =IF(#REF!="Header",#REF!,IF(#REF!="Item",IFERROR(LOOKUP(2,1/($A$2:A85="Header"),$B$2:B85),""),"")) -> #REF!
L97: =IF(#REF!="Header",#REF!,IF(#REF!="Item",IFERROR(LOOKUP(2,1/($A$2:A85="Header"),$B$2:B85),""),"")) -> #REF!
L98: =IF(A86="Header",B86,IF(A86="Item",IFERROR(LOOKUP(2,1/($A$2:A86="Header"),$B$2:B86),""),""))
L99: =IF(A87="Header",B87,IF(A87="Item",IFERROR(LOOKUP(2,1/($A$2:A87="Header"),$B$2:B87),""),""))
L100: =IF(A89="Header",B88,IF(A89="Item",IFERROR(LOOKUP(2,1/($A$2:A89="Header"),$B$2:B88),""),""))
L101: =IF(A90="Header",B89,IF(A90="Item",IFERROR(LOOKUP(2,1/($A$2:A90="Header"),$B$2:B89),""),""))
L102: =IF(A91="Header",B90,IF(A91="Item",IFERROR(LOOKUP(2,1/($A$2:A91="Header"),$B$2:B90),""),""))
L103: =IF(A92="Header",B92,IF(A92="Item",IFERROR(LOOKUP(2,1/($A$2:A92="Header"),$B$2:B92),""),""))
L104: =IF(A93="Header",B93,IF(A93="Item",IFERROR(LOOKUP(2,1/($A$2:A93="Header"),$B$2:B93),""),""))
L105: =IF(A94="Header",B94,IF(A94="Item",IFERROR(LOOKUP(2,1/($A$2:A94="Header"),$B$2:B94),""),""))
L106: =IF(A95="Header",B95,IF(A95="Item",IFERROR(LOOKUP(2,1/($A$2:A95="Header"),$B$2:B95),""),""))
L107: =IF(A96="Header",B96,IF(A96="Item",IFERROR(LOOKUP(2,1/($A$2:A96="Header"),$B$2:B96),""),""))
L108: =IF(A97="Header",B97,IF(A97="Item",IFERROR(LOOKUP(2,1/($A$2:A97="Header"),$B$2:B97),""),""))
L109: =IF(A98="Header",B98,IF(A98="Item",IFERROR(LOOKUP(2,1/($A$2:A98="Header"),$B$2:B98),""),""))
L110: =IF(A99="Header",B99,IF(A99="Item",IFERROR(LOOKUP(2,1/($A$2:A99="Header"),$B$2:B99),""),""))
L111: =IF(A100="Header",B100,IF(A100="Item",IFERROR(LOOKUP(2,1/($A$2:A100="Header"),$B$2:B100),""),""))
L112: =IF(A101="Header",B101,IF(A101="Item",IFERROR(LOOKUP(2,1/($A$2:A101="Header"),$B$2:B101),""),""))
...

Sheet Rates & Settings
A1: Mettro Estimating Guide & Rates
A3: GST % | B3: 0.1
A4: Contingency % | B4: 0.1
A5: Retainer / commitment discount % | B5: 0
A6: After-hours multiplier | B6: 2
A8: Role / category | B8: Rate ex GST | D8: Row Types
A9: Strategy | B9: 270 | D9: Header
A10: Project Management | B10: 210 | D10: Item
A11: Design | B11: 210 | D11: Spacer
A12: Development | B12: 230
A13: Integration & Technical | B13: 250
A14: Digital Marketing | B14: 220
A15: Copywriting | B15: 210
A16: Content Entry | B16: 170
A17: SEO/AEO/GEO | B17: 210
A18: Quality Assurance | B18: 170
A19: Standard Support | B19: 200
A20: 12-Month Support Plan | B20: 170
A21: External Contractor | B21: 200
